gesund_val_library/__init__.py
gesund_val_library/problem_type_factory.py
gesund_val_library/run_meta_validation.py
gesund_val_library/run_validation.py
gesund_val_library/validation.py
gesund_val_library/metrics/__init__.py
gesund_val_library/metrics/__pycache__/__init__.cpython-38.pyc
gesund_val_library/metrics/classification/__init__.py
gesund_val_library/metrics/classification/classification_metric_plot.py
gesund_val_library/metrics/classification/create_validation.py
gesund_val_library/metrics/classification/__pycache__/__init__.cpython-38.pyc
gesund_val_library/metrics/classification/__pycache__/classification_metric_plot.cpython-38.pyc
gesund_val_library/metrics/classification/__pycache__/create_validation.cpython-38.pyc
gesund_val_library/metrics/classification/__pycache__/metrics.cpython-38.pyc
gesund_val_library/metrics/classification/metrics/__init__.py
gesund_val_library/metrics/classification/metrics/accuracy.py
gesund_val_library/metrics/classification/metrics/auc.py
gesund_val_library/metrics/classification/metrics/confusion_matrix.py
gesund_val_library/metrics/classification/metrics/dataset_stats.py
gesund_val_library/metrics/classification/metrics/lift_chart.py
gesund_val_library/metrics/classification/metrics/most_confused.py
gesund_val_library/metrics/classification/metrics/stats_tables.py
gesund_val_library/metrics/classification/metrics/threshold.py
gesund_val_library/metrics/classification/metrics/top_losses.py
gesund_val_library/metrics/classification/metrics/__pycache__/__init__.cpython-38.pyc
gesund_val_library/metrics/classification/metrics/__pycache__/accuracy.cpython-38.pyc
gesund_val_library/metrics/classification/metrics/__pycache__/auc.cpython-38.pyc
gesund_val_library/metrics/classification/metrics/__pycache__/confusion_matrix.cpython-38.pyc
gesund_val_library/metrics/classification/metrics/__pycache__/dataset_stats.cpython-38.pyc
gesund_val_library/metrics/classification/metrics/__pycache__/lift_chart.cpython-38.pyc
gesund_val_library-0.3.17.dist-info/LICENSE
gesund_val_library-0.3.17.dist-info/METADATA
gesund_val_library-0.3.17.dist-info/WHEEL
gesund_val_library-0.3.17.dist-info/dependency_links.txt
gesund_val_library-0.3.17.dist-info/top_level.txt
gesund_val_library-0.3.17.dist-info/RECORD
