Metadata-Version: 2.1
Name: gesund-val-library
Version: 0.3.17
Summary: Gesund.ai package for running validation metrics for classification, semantic segmentation, instance segmentation, and object detection models.
Home-page: https://github.com/gesund-ai/gesund_val_library
Author: Gesund AI
Author-email: hammadbink@gmail.com
License: MIT
Platform: UNKNOWN
Classifier: Programming Language :: Python :: 3
Classifier: License :: OSI Approved :: MIT License
Classifier: Operating System :: OS Independent
Requires-Python: >=3.6
Requires-Dist: bson
Requires-Dist: dictances==1.5.3
Requires-Dist: jsonschema
Requires-Dist: miseval==1.2.2
Requires-Dist: numba==0.55.2
Requires-Dist: numpy==1.21.6
Requires-Dist: opencv-python
Requires-Dist: pandas
Requires-Dist: pycocotools
Requires-Dist: scikit-learn
Requires-Dist: seaborn
Requires-Dist: tqdm
